radixlib/__init__.py
radixlib/constants.py
radixlib/derive.py
radixlib/network.py
radixlib/provider.py
radixlib/serializable.py
radixlib/signer.py
radixlib/utils.py
radixlib/wallet.py
radixlib/actions/__init__.py
radixlib/actions/action_builder.py
radixlib/actions/burn_tokens.py
radixlib/actions/create_token_definition.py
radixlib/actions/mint_tokens.py
radixlib/actions/register_validator.py
radixlib/actions/stake_tokens.py
radixlib/actions/transfer_tokens.py
radixlib/actions/unregister_validator.py
radixlib/actions/unstake_tokens.py
radixlib/api_types/__init__.py
radixlib/api_types/token_amount.py
radixlib/api_types/identifiers/__init__.py
radixlib/api_types/identifiers/account_identifier.py
radixlib/api_types/identifiers/network_identifier.py
radixlib/api_types/identifiers/state_identifier.py
radixlib/api_types/identifiers/token_identifier.py
radixlib/api_types/identifiers/transaction_identifier.py
radixlib/api_types/identifiers/validator_identifier.py
radixlib/parsers/__init__.py
radixlib/parsers/base_parser.py
radixlib/parsers/default_parser.py
radixlib/parsers/no_parser.py
radixlib-1.1.1.dist-info/LICENSE
radixlib-1.1.1.dist-info/METADATA
radixlib-1.1.1.dist-info/WHEEL
radixlib-1.1.1.dist-info/top_level.txt
radixlib-1.1.1.dist-info/RECORD
