Metadata-Version: 2.1
Name: radixlib
Version: 1.1.1
Summary: A Python API wrapper for the Gateway API of the Radix Blockchain.
Home-page: https://github.com/0xOmarA/RadixLib
Author: Omar Abdulla
Author-email: OmarAbdulla7@hotmail.com
Project-URL: Bug Tracker, https://github.com/0xOmarA/RadixLib/issues
Classifier: Programming Language :: Python :: 3
Classifier: Programming Language :: Python :: 3.7
Classifier: Programming Language :: Python :: 3.8
Classifier: Programming Language :: Python :: 3.9
Classifier: Programming Language :: Python :: 3.10
Classifier: Programming Language :: Python :: 3.11
Classifier: Natural Language :: English
Classifier: Operating System :: OS Independent
Classifier: License :: OSI Approved :: MIT License
Requires-Python: >=3.7
License-File: LICENSE
Requires-Dist: requests
Requires-Dist: dateparser
Requires-Dist: pycryptodome
Requires-Dist: mnemonic
Requires-Dist: hdwallet
Requires-Dist: bech32
Requires-Dist: cryptography
Requires-Dist: pyjwt[crypto]
Provides-Extra: dev
Requires-Dist: check-manifest ; extra == 'dev'
Requires-Dist: twine ; extra == 'dev'
